pyglet_desper/__init__.py
pyglet_desper/loop.py
pyglet_desper/model.py
pyglet_desper/logic/__init__.py
pyglet_desper/logic/sync.py
pyglet_desper-1.0.0.dist-info/licenses/LICENSE
pyglet_desper-1.0.0.dist-info/METADATA
pyglet_desper-1.0.0.dist-info/WHEEL
pyglet_desper-1.0.0.dist-info/top_level.txt
pyglet_desper-1.0.0.dist-info/RECORD
