Metadata-Version: 2.4
Name: pyglet-desper
Version: 1.0.0
Summary: Extension package for desper and pyglet interoperation
Home-page: https://github.com/Ball-Man/pyglet-desper
Author: Francesco Mistri
Author-email: franc.mistri@gmail.com
License: MIT
Classifier: Intended Audience :: Developers
Classifier: Programming Language :: Python :: 3 :: Only
Classifier: Topic :: Games/Entertainment
Requires-Python: >=3.9
License-File: LICENSE
Requires-Dist: desper>=1.1.1
Requires-Dist: pyglet<2.2,>=2.1.0
Dynamic: author
Dynamic: author-email
Dynamic: classifier
Dynamic: description
Dynamic: description-content-type
Dynamic: home-page
Dynamic: license
Dynamic: license-file
Dynamic: requires-dist
Dynamic: requires-python
Dynamic: summary
